adfsmail/__init__.py
adfsmail/adfsmail/__init__.py
adfsmail/adfsmail/mail.py
adfsmail-1.1.dist-info/METADATA
adfsmail-1.1.dist-info/WHEEL
adfsmail-1.1.dist-info/top_level.txt
adfsmail-1.1.dist-info/RECORD
