Metadata-Version: 2.1
Name: adfsmail
Version: 1.1
Summary: Библиотека для работы с почтой ADFS
Home-page: UNKNOWN
License: UNKNOWN
Platform: UNKNOWN
Requires-Dist: lxml
Requires-Dist: requests
Requires-Dist: requests-ntlm
Requires-Dist: websocket-client
